pyballistic_exts/__init__.py
pyballistic_exts/base_engine.cp313-win32.pyd
pyballistic_exts/base_engine.pxd
pyballistic_exts/base_engine.pyi
pyballistic_exts/base_engine.pyx
pyballistic_exts/base_traj_seq.cp313-win32.pyd
pyballistic_exts/base_traj_seq.pxd
pyballistic_exts/base_traj_seq.pyx
pyballistic_exts/cy_bindings.cp313-win32.pyd
pyballistic_exts/cy_bindings.pxd
pyballistic_exts/cy_bindings.pyx
pyballistic_exts/euler_engine.cp313-win32.pyd
pyballistic_exts/euler_engine.pyi
pyballistic_exts/euler_engine.pyx
pyballistic_exts/rk4_engine.cp313-win32.pyd
pyballistic_exts/rk4_engine.pyi
pyballistic_exts/rk4_engine.pyx
pyballistic_exts/trajectory_data.cp313-win32.pyd
pyballistic_exts/trajectory_data.pxd
pyballistic_exts/trajectory_data.pyi
pyballistic_exts/trajectory_data.pyx
pyballistic_exts/v3d.pxd
pyballistic_exts/build/pyballistic_exts/base_engine.c
pyballistic_exts/build/pyballistic_exts/base_traj_seq.c
pyballistic_exts/build/pyballistic_exts/cy_bindings.c
pyballistic_exts/build/pyballistic_exts/euler_engine.c
pyballistic_exts/build/pyballistic_exts/rk4_engine.c
pyballistic_exts/build/pyballistic_exts/trajectory_data.c
pyballistic_exts/include/basetraj_seq.h
pyballistic_exts/include/bclib.h
pyballistic_exts/include/bind.h
pyballistic_exts/include/v3d.h
pyballistic_exts/src/bclib.c
pyballistic_exts/src/bind.c
pyballistic_exts/src/v3d.c
pyballistic_exts-2.2.0.dist-info/licenses/LICENSE
pyballistic_exts-2.2.0.dist-info/METADATA
pyballistic_exts-2.2.0.dist-info/WHEEL
pyballistic_exts-2.2.0.dist-info/entry_points.txt
pyballistic_exts-2.2.0.dist-info/top_level.txt
pyballistic_exts-2.2.0.dist-info/RECORD
