Metadata-Version: 2.4
Name: pyballistic.exts
Version: 2.2.0
Summary: LGPL library for small arms ballistic calculations (Python 3)
Author-email: o-murphy <thehelixpg@gmail.com>, dbookstaber <bookstaber@gmail.com>
Project-URL: Homepage, https://github.com/dbookstaber/pyballistic
Project-URL: Bug Reports, https://github.com/dbookstaber/pyballistic/issues
Project-URL: Source, https://github.com/dbookstaber/pyballistic
Keywords: pyballistic,ballistics,Cython,ballistic calculator,python,python3
Classifier: Intended Audience :: Developers
Classifier: Natural Language :: English
Classifier: Programming Language :: Python
Classifier: Topic :: Software Development :: Libraries :: Python Modules
Classifier: Programming Language :: Python :: 3
Classifier: Programming Language :: Python :: 3 :: Only
Classifier: Programming Language :: Python :: 3.9
Classifier: Programming Language :: Python :: 3.10
Classifier: Programming Language :: Python :: 3.11
Classifier: Programming Language :: Python :: 3.12
Classifier: Programming Language :: Python :: 3.13
Classifier: Operating System :: OS Independent
Classifier: Programming Language :: Python :: Implementation :: CPython
Requires-Python: >=3.9
License-File: LICENSE
Provides-Extra: dev
Requires-Dist: cython; extra == "dev"
Requires-Dist: build; extra == "dev"
Requires-Dist: setuptools; extra == "dev"
Requires-Dist: cibuildwheel; extra == "dev"
Dynamic: license-file
